{
  "4B.101..GP": {
    "latitude": 31.78592,
    "longitude": -106.22352,
    "elevation(m)": 1226,
    "unit": "m/s",
    "component": [
      "1",
      "2",
      "Z"
    ],
    "response": [
      1507118400.0,
      1507118400.0,
      1507118400.0
    ]
  },
  "4B.102..GP": {
    "latitude": 31.7036,
    "longitude": -106.33703,
    "elevation(m)": 1118,
    "unit": "m/s",
    "component": [
      "1",
      "2",
      "Z"
    ],
    "response": [
      1507118400.0,
      1507118400.0,
      1507118400.00001
    ]
  },
  "4B.103..GP": {
    "latitude": 31.85575,
    "longitude": -106.52372,
    "elevation(m)": 1345,
    "unit": "m/s",
    "component": [
      "1",
      "2",
      "Z"
    ],
    "response": [
      1507118400.0,
      1507118400.0,
      1507118400.00002
    ]
  },
  "4B.104..GP": {
    "latitude": 31.7987,
    "longitude": -106.54338,
    "elevation(m)": 1159,
    "unit": "m/s",
    "component": [
      "1",
      "2",
      "Z"
    ],
    "response": [
      1507118400.0,
      1507118400.0,
      1507118400.00003
    ]
  },
  "4B.105..GP": {
    "latitude": 31.62117,
    "longitude": -106.27982,
    "elevation(m)": 1113,
    "unit": "m/s",
    "component": [
      "1",
      "2",
      "Z"
    ],
    "response": [
      1507118400.0,
      1507118400.0,
      1507118400.00004
    ]
  },
  "4B.106..GP": {
    "latitude": 31.86317,
    "longitude": -106.54792,
    "elevation(m)": 1261,
    "unit": "m/s",
    "component": [
      "1",
      "2",
      "Z"
    ],
    "response": [
      1507118400.0,
      1507118400.0,
      1507118400.00005
    ]
  },
  "4B.107..GP": {
    "latitude": 31.75968,
    "longitude": -106.48373,
    "elevation(m)": 1146,
    "unit": "m/s",
    "component": [
      "1",
      "2",
      "Z"
    ],
    "response": [
      1507118400.0,
      1507118400.0,
      1507118400.00006
    ]
  },
  "4B.108..GP": {
    "latitude": 31.7719,
    "longitude": -106.50648,
    "elevation(m)": 1160,
    "unit": "m/s",
    "component": [
      "1",
      "2",
      "Z"
    ],
    "response": [
      1507118400.0,
      1507118400.0,
      1507118400.00007
    ]
  },
  "4B.109..GP": {
    "latitude": 31.75345,
    "longitude": -106.48653,
    "elevation(m)": 1138,
    "unit": "m/s",
    "component": [
      "1",
      "2",
      "Z"
    ],
    "response": [
      1507118400.0,
      1507118400.0,
      1507118400.00008
    ]
  },
  "4B.110..GP": {
    "latitude": 31.78133,
    "longitude": -106.49904,
    "elevation(m)": 1215,
    "unit": "m/s",
    "component": [
      "1",
      "2",
      "Z"
    ],
    "response": [
      1507118400.0,
      1507118400.0,
      1507118400.00009
    ]
  },
  "4B.111..GP": {
    "latitude": 31.7748,
    "longitude": -106.45907,
    "elevation(m)": 1138,
    "unit": "m/s",
    "component": [
      "1",
      "2",
      "Z"
    ],
    "response": [
      1507118400.0,
      1507118400.0,
      1507118400.0001
    ]
  },
  "4B.112..GP": {
    "latitude": 31.79598,
    "longitude": -106.54527,
    "elevation(m)": 1166,
    "unit": "m/s",
    "component": [
      "1",
      "2",
      "Z"
    ],
    "response": [
      1507118400.0,
      1507118400.0,
      1507118400.00011
    ]
  },
  "4B.113..GP": {
    "latitude": 31.7979,
    "longitude": -106.54528,
    "elevation(m)": 1162,
    "unit": "m/s",
    "component": [
      "1",
      "2",
      "Z"
    ],
    "response": [
      1507118400.0,
      1507118400.0,
      1507118400.00012
    ]
  },
  "4B.114..GP": {
    "latitude": 31.7792,
    "longitude": -106.3186,
    "elevation(m)": 1209,
    "unit": "m/s",
    "component": [
      "1",
      "2",
      "Z"
    ],
    "response": [
      1507118400.0,
      1507118400.0,
      1507118400.00013
    ]
  },
  "4B.115..GP": {
    "latitude": 31.739,
    "longitude": -106.27523,
    "elevation(m)": 1215,
    "unit": "m/s",
    "component": [
      "1",
      "2",
      "Z"
    ],
    "response": [
      1507118400.0,
      1507118400.0,
      1507118400.00014
    ]
  },
  "4B.116..GP": {
    "latitude": 31.67412,
    "longitude": -106.28442,
    "elevation(m)": 1107,
    "unit": "m/s",
    "component": [
      "1",
      "2",
      "Z"
    ],
    "response": [
      1507118400.0,
      1507118400.0,
      1507118400.00015
    ]
  },
  "4B.117..GP": {
    "latitude": 31.69102,
    "longitude": -106.32775,
    "elevation(m)": 1116,
    "unit": "m/s",
    "component": [
      "1",
      "2",
      "Z"
    ],
    "response": [
      1507118400.0,
      1507118400.0,
      1507118400.00016
    ]
  },
  "4B.118..GP": {
    "latitude": 31.67592,
    "longitude": -106.24282,
    "elevation(m)": 1176,
    "unit": "m/s",
    "component": [
      "1",
      "2",
      "Z"
    ],
    "response": [
      1507118400.0,
      1507118400.0,
      1507118400.00017
    ]
  },
  "4B.119..GP": {
    "latitude": 31.5915,
    "longitude": -106.22598,
    "elevation(m)": 1109,
    "unit": "m/s",
    "component": [
      "1",
      "2",
      "Z"
    ],
    "response": [
      1507118400.0,
      1507118400.0,
      1507118400.00018
    ]
  },
  "4B.120..GP": {
    "latitude": 31.58477,
    "longitude": -106.27273,
    "elevation(m)": 1110,
    "unit": "m/s",
    "component": [
      "1",
      "2",
      "Z"
    ],
    "response": [
      1507118400.0,
      1507118400.0,
      1507118400.00019
    ]
  },
  "4B.121..GP": {
    "latitude": 31.79828,
    "longitude": -106.54173,
    "elevation(m)": 1166,
    "unit": "m/s",
    "component": [
      "1",
      "2",
      "Z"
    ],
    "response": [
      1507118400.0,
      1507118400.0,
      1507118400.0002
    ]
  },
  "4B.122..GP": {
    "latitude": 31.68172,
    "longitude": -106.17081,
    "elevation(m)": 1222,
    "unit": "m/s",
    "component": [
      "1",
      "2",
      "Z"
    ],
    "response": [
      1507118400.0,
      1507118400.0,
      1507118400.00021
    ]
  },
  "4B.123..GP": {
    "latitude": 31.77455,
    "longitude": -106.42145,
    "elevation(m)": 1136,
    "unit": "m/s",
    "component": [
      "1",
      "2",
      "Z"
    ],
    "response": [
      1507118400.0,
      1507118400.0,
      1507118400.00022
    ]
  },
  "4B.124..GP": {
    "latitude": 31.50367,
    "longitude": -106.15928,
    "elevation(m)": 1100,
    "unit": "m/s",
    "component": [
      "1",
      "2",
      "Z"
    ],
    "response": [
      1507118400.0,
      1507118400.0,
      1507118400.00023
    ]
  },
  "4B.125..GP": {
    "latitude": 31.7401,
    "longitude": -106.34132,
    "elevation(m)": 1140,
    "unit": "m/s",
    "component": [
      "1",
      "2",
      "Z"
    ],
    "response": [
      1507118400.0,
      1507118400.0,
      1507118400.00024
    ]
  },
  "4B.126..GP": {
    "latitude": 31.7971,
    "longitude": -106.53987,
    "elevation(m)": 1176,
    "unit": "m/s",
    "component": [
      "1",
      "2",
      "Z"
    ],
    "response": [
      1507118400.0,
      1507118400.0,
      1507118400.00025
    ]
  },
  "4B.127..GP": {
    "latitude": 31.76893,
    "longitude": -106.44842,
    "elevation(m)": 1130,
    "unit": "m/s",
    "component": [
      "1",
      "2",
      "Z"
    ],
    "response": [
      1507118400.0,
      1507118400.0,
      1507118400.00026
    ]
  },
  "4B.128..GP": {
    "latitude": 31.78193,
    "longitude": -106.28285,
    "elevation(m)": 1210,
    "unit": "m/s",
    "component": [
      "1",
      "2",
      "Z"
    ],
    "response": [
      1507118400.0,
      1507118400.0,
      1507118400.00027
    ]
  },
  "4B.129..GP": {
    "latitude": 31.73618,
    "longitude": -106.37883,
    "elevation(m)": 1127,
    "unit": "m/s",
    "component": [
      "1",
      "2",
      "Z"
    ],
    "response": [
      1507118400.0,
      1507118400.0,
      1507118400.00028
    ]
  },
  "4B.130..GP": {
    "latitude": 31.79482,
    "longitude": -106.54077,
    "elevation(m)": 1211,
    "unit": "m/s",
    "component": [
      "1",
      "2",
      "Z"
    ],
    "response": [
      1507118400.0,
      1507118400.0,
      1507118400.00029
    ]
  },
  "4B.131..GP": {
    "latitude": 31.75802,
    "longitude": -106.47565,
    "elevation(m)": 1133,
    "unit": "m/s",
    "component": [
      "1",
      "2",
      "Z"
    ],
    "response": [
      1507118400.0,
      1507118400.0,
      1507118400.0003
    ]
  },
  "4B.132..GP": {
    "latitude": 31.77968,
    "longitude": -106.40772,
    "elevation(m)": 1173,
    "unit": "m/s",
    "component": [
      "1",
      "2",
      "Z"
    ],
    "response": [
      1507118400.0,
      1507118400.0,
      1507118400.00031
    ]
  },
  "4B.133..GP": {
    "latitude": 31.78713,
    "longitude": -106.44847,
    "elevation(m)": 1145,
    "unit": "m/s",
    "component": [
      "1",
      "2",
      "Z"
    ],
    "response": [
      1507118400.0,
      1507118400.0,
      1507118400.00032
    ]
  },
  "4B.134..GP": {
    "latitude": 31.79393,
    "longitude": -106.53873,
    "elevation(m)": 1204,
    "unit": "m/s",
    "component": [
      "1",
      "2",
      "Z"
    ],
    "response": [
      1507118400.0,
      1507118400.0,
      1507118400.00033
    ]
  },
  "4B.135..GP": {
    "latitude": 31.8312,
    "longitude": -106.58278,
    "elevation(m)": 1139,
    "unit": "m/s",
    "component": [
      "1",
      "2",
      "Z"
    ],
    "response": [
      1507118400.0,
      1507118400.0,
      1507118400.00034
    ]
  },
  "4B.136..GP": {
    "latitude": 31.77404,
    "longitude": -106.3444,
    "elevation(m)": 1205,
    "unit": "m/s",
    "component": [
      "1",
      "2",
      "Z"
    ],
    "response": [
      1507118400.0,
      1507118400.0,
      1507118400.00035
    ]
  },
  "4B.137..GP": {
    "latitude": 31.81772,
    "longitude": -106.17635,
    "elevation(m)": 1232,
    "unit": "m/s",
    "component": [
      "1",
      "2",
      "Z"
    ],
    "response": [
      1507118400.0,
      1507118400.0,
      1507118400.00036
    ]
  },
  "4B.138..GP": {
    "latitude": 31.76629,
    "longitude": -106.49337,
    "elevation(m)": 1156,
    "unit": "m/s",
    "component": [
      "1",
      "2",
      "Z"
    ],
    "response": [
      1507118400.0,
      1507118400.0,
      1507118400.00037
    ]
  },
  "4B.139..GP": {
    "latitude": 31.73677,
    "longitude": -106.3515,
    "elevation(m)": 1123,
    "unit": "m/s",
    "component": [
      "1",
      "2",
      "Z"
    ],
    "response": [
      1507118400.0,
      1507118400.0,
      1507118400.00038
    ]
  },
  "4B.140..GP": {
    "latitude": 31.79507,
    "longitude": -106.54402,
    "elevation(m)": 1175,
    "unit": "m/s",
    "component": [
      "1",
      "2",
      "Z"
    ],
    "response": [
      1507118400.0,
      1507118400.0,
      1507118400.00039
    ]
  },
  "4B.141..GP": {
    "latitude": 31.81888,
    "longitude": -106.56,
    "elevation(m)": 1142,
    "unit": "m/s",
    "component": [
      "1",
      "2",
      "Z"
    ],
    "response": [
      1507118400.0,
      1507118400.0,
      1507118400.0004
    ]
  },
  "4B.142..GP": {
    "latitude": 31.78857,
    "longitude": -106.46942,
    "elevation(m)": 1190,
    "unit": "m/s",
    "component": [
      "1",
      "2",
      "Z"
    ],
    "response": [
      1507118400.0,
      1507118400.0,
      1507118400.00041
    ]
  },
  "4B.143..GP": {
    "latitude": 31.80067,
    "longitude": -106.54055,
    "elevation(m)": 1137,
    "unit": "m/s",
    "component": [
      "1",
      "2",
      "Z"
    ],
    "response": [
      1507118400.0,
      1507118400.0,
      1507118400.00042
    ]
  },
  "4B.144..GP": {
    "latitude": 31.75512,
    "longitude": -106.28517,
    "elevation(m)": 1218,
    "unit": "m/s",
    "component": [
      "1",
      "2",
      "Z"
    ],
    "response": [
      1507118400.0,
      1507118400.0,
      1507118400.00043
    ]
  },
  "4B.145..GP": {
    "latitude": 31.92143,
    "longitude": -106.41803,
    "elevation(m)": 1210,
    "unit": "m/s",
    "component": [
      "1",
      "2",
      "Z"
    ],
    "response": [
      1507118400.0,
      1507118400.0,
      1507118400.00044
    ]
  },
  "4B.146..GP": {
    "latitude": 31.81952,
    "longitude": -106.4526,
    "elevation(m)": 1232,
    "unit": "m/s",
    "component": [
      "1",
      "2",
      "Z"
    ],
    "response": [
      1507118400.0,
      1507118400.0,
      1507118400.00045
    ]
  },
  "4B.147..GP": {
    "latitude": 31.857,
    "longitude": -106.545,
    "elevation(m)": 1256,
    "unit": "m/s",
    "component": [
      "1",
      "2",
      "Z"
    ],
    "response": [
      1507118400.0,
      1507118400.0,
      1507118400.00046
    ]
  },
  "4B.148..GP": {
    "latitude": 31.7505,
    "longitude": -106.28951,
    "elevation(m)": 1220,
    "unit": "m/s",
    "component": [
      "1",
      "2",
      "Z"
    ],
    "response": [
      1507118400.0,
      1507118400.0,
      1507118400.00047
    ]
  },
  "4B.149..GP": {
    "latitude": 31.80118,
    "longitude": -106.46692,
    "elevation(m)": 1229,
    "unit": "m/s",
    "component": [
      "1",
      "2",
      "Z"
    ],
    "response": [
      1507118400.0,
      1507118400.0,
      1507118400.00048
    ]
  },
  "4B.150..GP": {
    "latitude": 31.779,
    "longitude": -106.24025,
    "elevation(m)": 1216,
    "unit": "m/s",
    "component": [
      "1",
      "2",
      "Z"
    ],
    "response": [
      1507118400.0,
      1507118400.0,
      1507118400.00049
    ]
  }
}